LICENSE.md
README.md
pyproject.toml
setup.py
lm_eval/__init__.py
lm_eval/__main__.py
lm_eval/config.py
lm_eval/evaluator.py
lm_eval/logger.py
lm_eval/scholar_api.py
lm_eval/utils.py
lm_eval/api/__init__.py
lm_eval/api/filter.py
lm_eval/api/instance.py
lm_eval/api/metrics.py
lm_eval/api/model.py
lm_eval/api/registry.py
lm_eval/api/samplers.py
lm_eval/api/task.py
lm_eval/decontamination/__init__.py
lm_eval/decontamination/archiver.py
lm_eval/decontamination/decontaminate.py
lm_eval/decontamination/janitor.py
lm_eval/filters/__init__.py
lm_eval/filters/decontamination.py
lm_eval/filters/extraction.py
lm_eval/filters/selection.py
lm_eval/filters/transformation.py
lm_eval/models/__init__.py
lm_eval/models/anthropic_llms.py
lm_eval/models/dummy.py
lm_eval/models/gguf.py
lm_eval/models/huggingface.py
lm_eval/models/openai_completions.py
lm_eval/models/textsynth.py
lm_eval/models/vllm_causallms.py
lm_eval/prompts/__init__.py
lm_eval/tasks/README.md
lm_eval/tasks/__init__.py
lm_eval/tasks/__pycache__/__init__.cpython-39.pyc
lm_eval/tasks/__pycache__/anli.cpython-39.pyc
lm_eval/tasks/__pycache__/arc.cpython-39.pyc
lm_eval/tasks/__pycache__/arithmetic.cpython-39.pyc
lm_eval/tasks/__pycache__/asdiv.cpython-39.pyc
lm_eval/tasks/__pycache__/babi.cpython-39.pyc
lm_eval/tasks/__pycache__/bigbench.cpython-39.pyc
lm_eval/tasks/__pycache__/blimp.cpython-39.pyc
lm_eval/tasks/__pycache__/cbt.cpython-39.pyc
lm_eval/tasks/__pycache__/ceval.cpython-39.pyc
lm_eval/tasks/__pycache__/cmmlu.cpython-39.pyc
lm_eval/tasks/__pycache__/coqa.cpython-39.pyc
lm_eval/tasks/__pycache__/crowspairs.cpython-39.pyc
lm_eval/tasks/__pycache__/csatqa.cpython-39.pyc
lm_eval/tasks/__pycache__/drop.cpython-39.pyc
lm_eval/tasks/__pycache__/glue.cpython-39.pyc
lm_eval/tasks/__pycache__/gsm8k.cpython-39.pyc
lm_eval/tasks/__pycache__/haerae.cpython-39.pyc
lm_eval/tasks/__pycache__/headqa.cpython-39.pyc
lm_eval/tasks/__pycache__/hellaswag.cpython-39.pyc
lm_eval/tasks/__pycache__/hendrycks_ethics.cpython-39.pyc
sevals.egg-info/PKG-INFO
sevals.egg-info/SOURCES.txt
sevals.egg-info/dependency_links.txt
sevals.egg-info/entry_points.txt
sevals.egg-info/requires.txt
sevals.egg-info/top_level.txt
