Metadata-Version: 2.1
Name: sevals
Version: 0.0.3
Summary: A framework for evaluating language models
Author-email: Scholar Platforms <info@usescholar.org>
License: MIT
Classifier: Development Status :: 3 - Alpha
Classifier: Programming Language :: Python :: 3
Classifier: License :: OSI Approved :: MIT License
Classifier: Operating System :: OS Independent
Requires-Python: >=3.8
License-File: LICENSE.md
Requires-Dist: accelerate>=0.21.0
Requires-Dist: bullet
Requires-Dist: evaluate
Requires-Dist: datasets>=2.0.0
Requires-Dist: evaluate>=0.4.0
Requires-Dist: jsonlines
Requires-Dist: numexpr
Requires-Dist: peft>=0.2.0
Requires-Dist: print_color
Requires-Dist: pybind11>=2.6.2
Requires-Dist: pytablewriter
Requires-Dist: rouge-score>=0.0.4
Requires-Dist: sacrebleu>=1.5.0
Requires-Dist: scikit-learn>=0.24.1
Requires-Dist: sqlitedict
Requires-Dist: thefuzz
Requires-Dist: torch>=1.8
Requires-Dist: tqdm-multiprocess
Requires-Dist: transformers>=4.1
Requires-Dist: zstandard
Provides-Extra: dev
Requires-Dist: black; extra == "dev"
Requires-Dist: flake8; extra == "dev"
Requires-Dist: pre-commit; extra == "dev"
Requires-Dist: pytest; extra == "dev"
Requires-Dist: pytest-cov; extra == "dev"
Provides-Extra: linting
Requires-Dist: flake8; extra == "linting"
Requires-Dist: pylint; extra == "linting"
Requires-Dist: mypy; extra == "linting"
Requires-Dist: pre-commit; extra == "linting"
Provides-Extra: testing
Requires-Dist: pytest; extra == "testing"
Requires-Dist: pytest-cov; extra == "testing"
Requires-Dist: pytest-xdist; extra == "testing"
Provides-Extra: multilingual
Requires-Dist: nagisa>=0.2.7; extra == "multilingual"
Requires-Dist: jieba>=0.42.1; extra == "multilingual"
Requires-Dist: pycountry; extra == "multilingual"
Provides-Extra: math
Requires-Dist: sympy>=1.12; extra == "math"
Requires-Dist: antlr4-python3-runtime==4.11; extra == "math"
Provides-Extra: sentencepiece
Requires-Dist: sentencepiece>=0.1.98; extra == "sentencepiece"
Requires-Dist: protobuf>=4.22.1; extra == "sentencepiece"
Provides-Extra: anthropic
Requires-Dist: anthropic; extra == "anthropic"
Provides-Extra: openai
Requires-Dist: openai>=1.3.5; extra == "openai"
Requires-Dist: tiktoken; extra == "openai"
Provides-Extra: vllm
Requires-Dist: vllm; extra == "vllm"
Provides-Extra: all
Requires-Dist: sevals[dev]; extra == "all"
Requires-Dist: sevals[testing]; extra == "all"
Requires-Dist: sevals[linting]; extra == "all"
Requires-Dist: sevals[multilingual]; extra == "all"
Requires-Dist: sevals[sentencepiece]; extra == "all"
Requires-Dist: sevals[anthropic]; extra == "all"
Requires-Dist: sevals[openai]; extra == "all"
Requires-Dist: sevals[vllm]; extra == "all"
